horizon_infra_connectors/__init__.py
horizon_infra_connectors/errors.py
horizon_infra_connectors/argocd/__init__.py
horizon_infra_connectors/argocd/api.py
horizon_infra_connectors/argocd/models.py
horizon_infra_connectors/argocd/service.py
horizon_infra_connectors/git/__init__.py
horizon_infra_connectors/git/api.py
horizon_infra_connectors/git/bitbucket_api.py
horizon_infra_connectors/git/models.py
horizon_infra_connectors/git/service.py
horizon_infra_connectors/vault/__init__.py
horizon_infra_connectors/vault/api.py
horizon_infra_connectors/vault/models.py
horizon_infra_connectors/vault/service.py
horizon_infra_connectors-0.0.0.1.dev1.dist-info/METADATA
horizon_infra_connectors-0.0.0.1.dev1.dist-info/WHEEL
horizon_infra_connectors-0.0.0.1.dev1.dist-info/top_level.txt
horizon_infra_connectors-0.0.0.1.dev1.dist-info/RECORD
