Metadata-Version: 2.4
Name: horizon-infra-connectors
Version: 0.0.0.1.dev1
Summary: Async helpers that wrap Argo CD, Git providers, and Vault APIs.
Author: Yehonatan Magen, Alon Elimelech
Requires-Python: >=3.9
Requires-Dist: fastapi>=0.95
Requires-Dist: httpx>=0.24
Requires-Dist: loguru>=0.7
Requires-Dist: horizon-fastapi-template>=0.0.0.4.dev1
Requires-Dist: pyyaml>=6.0.3
Requires-Dist: pydantic>=2.0
Requires-Dist: pydantic-settings>=2.0
